{
  "groups": {
    "🔵 学习": { "color": "#3b82f6", "tags": ["学习🧐","看论文","实验室","制冷机","有效学习","组会&报告","讨论","琐事","英语讨论"] },
    "🟣 日常管理": { "color": "#a855f7", "tags": ["充分利用","爱呀","自己","家人","朋友","思考计划","时间","计划","记账","碎片时间","关于阅读","思考","情绪","哈哈哈","平凡一天","玉玉中","暴躁","滴滴答答","啊"] },
    "🟠 成长": { "color": "#f97316", "tags": ["成长","英语","阅读","书评","爱好","志愿实践","党","电影","ai"] },
    "🟢 运动": { "color": "#22c55e", "tags": ["运动","🚲自行车","🧘🏻‍♀️瑜伽","🏸羽毛球","🥊动感搏击","🤰🏻肚子"] },
    "🟡 娱乐": { "color": "#eab308", "tags": ["放松一下🎉","玩手机","影视","潜时间","未知流逝","效率极低","短视频漩涡","yell","小说漩涡"] },
    "🟢 生活": { "color": "#10b981", "tags": ["生活","吃饭饭","劳动","洗漱","各种"] },
    "⚫ 睡眠": { "color": "#64748b", "tags": ["睡觉","晚上","白天"] }
  }
}
